robot_mousekey/__init__.py
robot_mousekey/index.py
robot_mousekey/tests/__init__.py
robot_mousekey/tests/test_index.py
robot_mousekey-0.3.0.dist-info/METADATA
robot_mousekey-0.3.0.dist-info/WHEEL
robot_mousekey-0.3.0.dist-info/RECORD
